simplebot_cartv/__init__.py
simplebot_cartv/_version.py
simplebot_cartv-1.2.0.dist-info/LICENSE
simplebot_cartv-1.2.0.dist-info/METADATA
simplebot_cartv-1.2.0.dist-info/WHEEL
simplebot_cartv-1.2.0.dist-info/entry_points.txt
simplebot_cartv-1.2.0.dist-info/top_level.txt
simplebot_cartv-1.2.0.dist-info/RECORD
